vega/__init__.py
vega/algorithms/__init__.py
vega/algorithms/auto_loss/__init__.py
vega/algorithms/auto_loss/ada_segment.py
vega/algorithms/auto_loss/ada_segment_conf.py
vega/algorithms/auto_loss/adaptive_muti_loss.py
vega/algorithms/compression/__init__.py
vega/algorithms/compression/auto_prune/__init__.py
vega/algorithms/compression/auto_prune/auto_prune.py
vega/algorithms/compression/auto_prune/pruning.py
vega/algorithms/compression/prune_ea/__init__.py
vega/algorithms/compression/prune_ea/conf.py
vega/algorithms/compression/prune_ea/prune_codec.py
vega/algorithms/compression/prune_ea/prune_ea.py
vega/algorithms/compression/prune_ea/prune_search_space.py
vega/algorithms/compression/prune_ea/prune_trainer_callback.py
vega/algorithms/compression/prune_ea_mobilenet/__init__.py
vega/algorithms/compression/prune_ea_mobilenet/conf.py
vega/algorithms/compression/prune_ea_mobilenet/prune_mobilenet_codec.py
vega/algorithms/compression/prune_ea_mobilenet/prune_trainer_callback.py
vega/algorithms/compression/quant_ea/__init__.py
vega/algorithms/compression/quant_ea/conf.py
vega/algorithms/compression/quant_ea/quant_codec.py
vega/algorithms/compression/quant_ea/quant_ea.py
vega/algorithms/compression/quant_ea/quant_trainer_callback.py
vega/algorithms/data_augmentation/__init__.py
vega/algorithms/data_augmentation/pba_conf.py
vega/algorithms/data_augmentation/pba_hpo.py
vega/algorithms/data_augmentation/pba_trainer_callback.py
vega/algorithms/data_augmentation/common/__init__.py
vega/algorithms/data_augmentation/common/pba.py
vega/algorithms/data_augmentation/common/status_type.py
vega/algorithms/data_augmentation/cyclesr/__init__.py
vega/algorithms/data_augmentation/cyclesr/cyclesr_trainer_callback.py
vega/algorithms/data_augmentation/cyclesr/utils.py
vega/algorithms/hpo/__init__.py
vega/algorithms/hpo/asha_conf.py
vega/algorithms/hpo/asha_hpo.py
vega/algorithms/hpo/bayes.py
vega/algorithms/hpo/bayes_conf.py
vega/algorithms/hpo/bohb_conf.py
vega/algorithms/hpo/bohb_hpo.py
noah_vega-1.8.5.dist-info/LICENSE
noah_vega-1.8.5.dist-info/METADATA
noah_vega-1.8.5.dist-info/WHEEL
noah_vega-1.8.5.dist-info/entry_points.txt
noah_vega-1.8.5.dist-info/top_level.txt
noah_vega-1.8.5.dist-info/RECORD
