Metadata-Version: 2.1
Name: noah-vega
Version: 1.8.5
Summary: AutoML Toolkit
Home-page: https://github.com/huawei-noah/vega
Author: Huawei Noah's Ark Lab
Author-email: 
License: Apache License 2.0
Platform: UNKNOWN
Classifier: Programming Language :: Python :: 3
Classifier: License :: OSI Approved :: Apache Software License
Classifier: Operating System :: POSIX :: Linux
Requires-Python: >=3.6
Requires-Dist: thop
Requires-Dist: psutil
Requires-Dist: pillow
Requires-Dist: pyzmq
Requires-Dist: pandas
Requires-Dist: distributed
Requires-Dist: click
Requires-Dist: PyYAML
Requires-Dist: numpy
Requires-Dist: scipy
Requires-Dist: dill
Requires-Dist: scikit-learn
Requires-Dist: opencv-python
